rmsorn/__init__.py
rmsorn/rmsorn.py
rmsorn/tasks.py
rmsorn/utils.py
rmsorn-0.0.9.data/data/LICENSE
rmsorn-0.0.9.dist-info/LICENSE
rmsorn-0.0.9.dist-info/METADATA
rmsorn-0.0.9.dist-info/WHEEL
rmsorn-0.0.9.dist-info/top_level.txt
rmsorn-0.0.9.dist-info/RECORD
