Metadata-Version: 2.1
Name: rmsorn
Version: 0.0.9
Summary: Reward Modulated Self-Organizing Recurrent Neural Networks
Home-page: https://github.com/Saran-nns/rm_sorn
Author: Saranraj Nambusubramaniyan
Author-email: saran_nns@hotmail.com
License: OSI Approved :: MIT License
Keywords: Brain-Inspired Computing,Artificial Neural Networks,Neuro Informatics,Spiking Cortical Networks,Reinformcement Learning,Neural Connectomics,Neuroscience,Artificial General Intelligence,Neural Information Processing
Platform: UNKNOWN
Classifier: Development Status :: 3 - Alpha
Classifier: Topic :: Scientific/Engineering :: Artificial Intelligence
Classifier: License :: OSI Approved :: MIT License
Classifier: Programming Language :: Python :: 3
Classifier: Programming Language :: Python :: 3.5
Classifier: Programming Language :: Python :: 3.6
Classifier: Programming Language :: Python :: 3.7
Requires-Dist: numpy
Requires-Dist: configparser
Requires-Dist: tqdm
Requires-Dist: scipy
Requires-Dist: seaborn
